PyMerge/__init__.py
PyMerge/merge.py
PyMerge-0.2.0.dist-info/LICENSE.txt
PyMerge-0.2.0.dist-info/METADATA
PyMerge-0.2.0.dist-info/WHEEL
PyMerge-0.2.0.dist-info/top_level.txt
PyMerge-0.2.0.dist-info/RECORD
