Metadata-Version: 2.1
Name: PyMerge
Version: 0.2.0
Summary: Code File Merge Tool in Python.
Home-page: https://github.com/syys96/PyMerge
Author: Ryouko
Author-email: syysdgf@gmail.com
License: GPL
Platform: UNKNOWN
Classifier: License :: OSI Approved :: GNU General Public License v3 (GPLv3)
Classifier: Programming Language :: Python
Classifier: Programming Language :: Python :: 3
Classifier: Programming Language :: Python :: 3.6
Classifier: Programming Language :: Python :: Implementation :: CPython
Classifier: Programming Language :: Python :: Implementation :: PyPy
Requires-Python: >=3.6.0
License-File: LICENSE.txt
